openai_agents_sdk_mcp/__init__.py
openai_agents_sdk_mcp/documentation.py
openai_agents_sdk_mcp/server.py
openai_agents_sdk_mcp-1.1.0.dist-info/licenses/LICENSE
openai_agents_sdk_mcp-1.1.0.dist-info/METADATA
openai_agents_sdk_mcp-1.1.0.dist-info/WHEEL
openai_agents_sdk_mcp-1.1.0.dist-info/entry_points.txt
openai_agents_sdk_mcp-1.1.0.dist-info/top_level.txt
openai_agents_sdk_mcp-1.1.0.dist-info/RECORD
