Metadata-Version: 2.4
Name: openai-agents-sdk-mcp
Version: 1.1.0
Summary: MCP server for OpenAI Agents SDK documentation
Author-email: Gavin Zhang <gavinz0228@gmail.com>
License: MIT
Project-URL: Homepage, https://github.com/gavinz0228/openai-agents-sdk-mcp
Project-URL: Repository, https://github.com/gavinz0228/openai-agents-sdk-mcp
Project-URL: Documentation, https://github.com/gavinz0228/openai-agents-sdk-mcp#readme
Project-URL: Issues, https://github.com/gavinz0228/openai-agents-sdk-mcp/issues
Keywords: mcp,model-context-protocol,openai,agents,documentation,llm
Classifier: Development Status :: 4 - Beta
Classifier: Intended Audience :: Developers
Classifier: License :: OSI Approved :: MIT License
Classifier: Programming Language :: Python :: 3
Classifier: Programming Language :: Python :: 3.8
Classifier: Programming Language :: Python :: 3.9
Classifier: Programming Language :: Python :: 3.10
Classifier: Programming Language :: Python :: 3.11
Classifier: Programming Language :: Python :: 3.12
Classifier: Programming Language :: Python :: 3.13
Classifier: Topic :: Software Development :: Libraries :: Python Modules
Classifier: Topic :: Scientific/Engineering :: Artificial Intelligence
Requires-Python: >=3.8
License-File: LICENSE
Requires-Dist: requests>=2.31.0
Requires-Dist: beautifulsoup4>=4.12.0
Requires-Dist: lxml>=4.9.0
Requires-Dist: openai>=1.0.0
Requires-Dist: python-dotenv>=1.0.0
Requires-Dist: mcp>=1.0.0
Provides-Extra: dev
Requires-Dist: pytest>=7.0.0; extra == "dev"
Requires-Dist: pytest-asyncio>=0.21.0; extra == "dev"
Requires-Dist: black>=23.0.0; extra == "dev"
Requires-Dist: mypy>=1.0.0; extra == "dev"
Dynamic: license-file
